[{"id": 0, "poster_id": "id0", "title": "title0", "content": "content0", "offers": [""], "resolved": false, "chats": []},{"id": 1, "poster_id": "id1", "title": "title1", "content": "content1", "offers": [""], "resolved": false, "chats": []},{"id": 2, "poster_id": "id2", "title": "title2", "content": "content2", "offers": [""], "resolved": false, "chats": []},{"id": 3, "poster_id": "id3", "title": "title3", "content": "content3", "offers": [""], "resolved": false, "chats": []},{"id": 4, "poster_id": "id4", "title": "title4", "content": "content4", "offers": [""], "resolved": false, "chats": []}]  